    {
        "WardNo": 3,
        "Gender": {
            "Male": {
                "0-4":1620 ,
                "5-9": 1610,
                "10-14": 1785,
                "15-19": 1980,
                "20-24": 1955,
                "25-29": 1870,
                "30-34": 1675,
                "35-39": 1800,
                "40-44": 2100,
                "45-49": 2430,
                "50-54": 2240,
                "55-59": 2000,
                "60-64": 1715,
                "65-69": 1365,
                "70-74": 1120,
                "75-79": 870,
                "80-84": 585,
                "85 and over": 370

            },
            "Female": {
                "0-4": 1455 ,
                "5-9": 1560,
                "10-14": 1675,
                "15-19": 1860,
                "20-24": 1795,
                "25-29": 1850,
                "30-34": 1945,
                "35-39": 1995,
                "40-44": 2275,
                "45-49": 2330,
                "50-54": 2460,
                "55-59": 2155,
                "60-64": 2010,
                "65-69": 1945,
                "70-74": 1280,
                "75-79": 1050,
                "80-84": 775,
                "85 and over":775

            }
        },
        "TotalPopulation": 59840,
        "AfterTaxHousehold": {
            "0-19999": 2155 ,
            "20999-39999": 4645,
            "40999-59999": 4880,
            "60000-79999": 3080,
             "80000-99999": 2460,
            "100000 and over": 4290

        },
        "AfterTaxIndividual": {
            "0-19999": 17740,
            "20999-39999": 15490,
            "40999-59999": 8125,
            "60000-79999": 3365,
             "80000-99999": 995,
            "100000 and over": 795

        }
    }
